include/tbb/aggregator.h
include/tbb/aligned_space.h
include/tbb/atomic.h
include/tbb/blocked_range.h
include/tbb/blocked_range2d.h
include/tbb/blocked_range3d.h
include/tbb/blocked_rangeNd.h
include/tbb/cache_aligned_allocator.h
include/tbb/combinable.h
include/tbb/compat/condition_variable
include/tbb/compat/ppl.h
include/tbb/compat/thread
include/tbb/compat/tuple
include/tbb/concurrent_hash_map.h
include/tbb/concurrent_lru_cache.h
include/tbb/concurrent_map.h
include/tbb/concurrent_priority_queue.h
include/tbb/concurrent_queue.h
include/tbb/concurrent_set.h
include/tbb/concurrent_unordered_map.h
include/tbb/concurrent_unordered_set.h
include/tbb/concurrent_vector.h
include/tbb/critical_section.h
include/tbb/enumerable_thread_specific.h
include/tbb/flow_graph.h
include/tbb/flow_graph_abstractions.h
include/tbb/flow_graph_opencl_node.h
include/tbb/global_control.h
include/tbb/index.html
include/tbb/info.h
include/tbb/internal/_aggregator_impl.h
include/tbb/internal/_allocator_traits.h
include/tbb/internal/_concurrent_queue_impl.h
include/tbb/internal/_concurrent_skip_list_impl.h
include/tbb/internal/_concurrent_unordered_impl.h
include/tbb/internal/_deprecated_header_message_guard.h
include/tbb/internal/_flow_graph_async_msg_impl.h
include/tbb/internal/_flow_graph_body_impl.h
include/tbb/internal/_flow_graph_cache_impl.h
include/tbb/internal/_flow_graph_impl.h
include/tbb/internal/_flow_graph_indexer_impl.h
include/tbb/internal/_flow_graph_item_buffer_impl.h
include/tbb/internal/_flow_graph_join_impl.h
include/tbb/internal/_flow_graph_node_impl.h
include/tbb/internal/_flow_graph_node_set_impl.h
include/tbb/internal/_flow_graph_nodes_deduction.h
include/tbb/internal/_flow_graph_streaming_node.h
include/tbb/internal/_flow_graph_tagged_buffer_impl.h
include/tbb/internal/_flow_graph_trace_impl.h
include/tbb/internal/_flow_graph_types_impl.h
include/tbb/internal/_mutex_padding.h
include/tbb/internal/_node_handle_impl.h
include/tbb/internal/_range_iterator.h
pynanoinstantmeshes-0.0.3.dist-info/METADATA
pynanoinstantmeshes-0.0.3.dist-info/WHEEL
pynanoinstantmeshes-0.0.3.dist-info/RECORD
