Metadata-Version: 2.1
Name: pynanoinstantmeshes
Version: 0.0.3
Summary: Python nano binding for instant meshes
Author-Email: Mark Boss <hello@markboss.me>
Classifier: License :: OSI Approved :: BSD License
Requires-Python: >=3.8
